setup.py
rhoPorousMRFLTSPimpleFlux/__init__.py
rhoPorousMRFLTSPimpleFlux.egg-info/PKG-INFO
rhoPorousMRFLTSPimpleFlux.egg-info/SOURCES.txt
rhoPorousMRFLTSPimpleFlux.egg-info/dependency_links.txt
rhoPorousMRFLTSPimpleFlux.egg-info/entry_points.txt
rhoPorousMRFLTSPimpleFlux.egg-info/requires.txt
rhoPorousMRFLTSPimpleFlux.egg-info/top_level.txt
rhoPorousMRFLTSPimpleFlux.egg-info/zip-safe
rhoPorousMRFLTSPimpleFlux/r2_1_1/__init__.py